LICENSE
README.md
setup.cfg
setup.py
indecro/__init__.py
indecro/defaults.py
indecro/executor.py
indecro/job.py
indecro/rules.py
indecro/scheduler.py
indecro.egg-info/PKG-INFO
indecro.egg-info/SOURCES.txt
indecro.egg-info/dependency_links.txt
indecro.egg-info/top_level.txt
indecro/api/__init__.py
indecro/api/executor.py
indecro/api/job.py
indecro/api/rules.py
indecro/api/scheduler.py
indecro/api/storage.py
indecro/api/task.py
indecro/exceptions/__init__.py
indecro/exceptions/base.py
indecro/exceptions/job.py
indecro/exceptions/rule.py
indecro/exceptions/scheduler.py
indecro/storage/__init__.py
indecro/storage/base.py
indecro/storage/memory_storage.py