Metadata-Version: 2.1
Name: indecro
Version: 0.135
Summary: Python scheduler with task independency from scheduler, executor and others
Home-page: https://github.com/TypeHintsFun/indecro
Author: TypeHintsFun
Author-email: typehintsfun@gmail.com
License: MIT
Classifier: Operating System :: OS Independent
Classifier: Intended Audience :: Developers
Classifier: License :: OSI Approved :: MIT License
Classifier: Programming Language :: Python :: 3
Requires-Python: >=3.9
License-File: LICENSE
